LICENSE
README.md
setup.cfg
setup.py
chainbreaker_api/__init__.py
chainbreaker_api/client.py
chainbreaker_api.egg-info/PKG-INFO
chainbreaker_api.egg-info/SOURCES.txt
chainbreaker_api.egg-info/dependency_links.txt
chainbreaker_api.egg-info/requires.txt
chainbreaker_api.egg-info/top_level.txt